Workbook
Name Slicer_Order_Status: #N/A

Sheet object2
A3: Category | B3: Sum of Total_Sales_INR
A4: Beauty & Personal Care | B4: 81717.17
A5: Home & Kitchen | B5: 135444.96
A6: Fashion | B6: 138785.41
A7: Sports & Fitness | B7: 220490.66
A8: Electronics | B8: 760481.59
A9: Appliances | B9: 828543.62
A10: Grand Total | B10: 2165463.4

Sheet object3
A3: Category | B3: Count of Profit_INR
A4: Appliances | B4: 82
A5: Beauty & Personal Care | B5: 83
A6: Electronics | B6: 89
A7: Fashion | B7: 83
A8: Home & Kitchen | B8: 83
A9: Sports & Fitness | B9: 80
A10: Grand Total | B10: 500

Sheet object4
A3: Product | B3: Sum of Total_Sales_INR
A4: Cockatoo Motorized Multi-Function Treadmill | B4: 113061
A5: Godrej 1.5 Ton 3 Star Convertible Inverter AC | B5: 107486.4
A6: HP 15s 12th Gen Intel Core i3 Laptop | B6: 139803.2
A7: IFB 6kg 5 Star Fully Automatic Front Load Washing Machine | B7: 101957.5
A8: LG 7kg 5 Star Inverter Washing Machine | B8: 116832.5
A9: Mi Smart TV 43 Inch 4K Ultra HD Series | B9: 79996.8
A10: OnePlus Nord CE 3 Lite 5G | B10: 91995.4
A11: Samsung 253L 3 Star Inverter Frost-Free Refrigerator | B11: 107756
A12: Samsung Galaxy M34 5G Smartphone | B12: 72245.75
A13: Sony WH-1000XM5 Wireless ANC Headphones | B13: 134955
A14: Grand Total | B14: 1066089.6

Sheet object5
A3: Order_Status | B3: Count of Order_ID
A4: Cancelled | B4: 15
A5: Delivered | B5: 438
A6: In Transit | B6: 14
A7: Returned | B7: 25
A8: Shipped | B8: 8
A9: Grand Total | B9: 500
C22: in the above data 50% items was Delivered and rest of some issuses

Sheet Sheet1

Sheet object6
A3: Product | B3: Count of Profit_INR
A4: Faber 60cm 1000 m3/h Kitchen Chimney | B4: 1
A5: Fastrack Casual Analog Watch for Men | B5: 3
A6: Puma Men Smashic Casual Sneakers | B6: 5
A7: US Polo Assn Men Solid Slim Casual Shirt | B7: 4
A8: Van Heusen Men Athleisure Cotton Joggers | B8: 2
A9: Grand Total | B9: 15

Sheet object1
A1: Order_ID | B1: Order_Date | C1: Category | D1: Product | E1: Quantity | F1: Unit_Price_INR | G1: Discount_Pct | H1: Total_Sales_INR | I1: Profit_INR | J1: Payment_Method | K1: Fulfillment | L1: Order_Status | M1: Ship_State
A2: IN-2024-1001 | B2: 45295 | C2: Electronics | D2: boAt Rockerz 450 Bluetooth Headphones | E2: 2 | F2: 1499 | G2: 0.1 | H2: =ROUND(E2*F2*(1-G2), 2) -> 2698.2 | I2: =ROUND(_xludf.IFS(L2="Cancelled", 0, L2="Returned", -0.1*H2, C2="Electronics", 0.14*H2, C2="Appliances", 0.16*H2, C2="Fashion", 0.26*H2, C2="Home & Kitchen", 0.22*H2, C2="Beauty & Personal Care", 0.3*H2, C2="Sports & Fitness", 0.2*H2, TRUE, 0.15*H2), 2) -> #NAME? | J2: UPI | K2: Fulfilled by Amazon | L2: Delivered | M2: Maharashtra
A3: IN-2024-1002 | B3: 45297 | C3: Fashion | D3: Levi's Men Slim Fit Jeans | E3: 1 | F3: 2499 | G3: 0.2 | H3: =ROUND(E3*F3*(1-G3), 2) -> 1999.2 | I3: =ROUND(_xludf.IFS(L3="Cancelled", 0, L3="Returned", -0.1*H3, C3="Electronics", 0.14*H3, C3="Appliances", 0.16*H3, C3="Fashion", 0.26*H3, C3="Home & Kitchen", 0.22*H3, C3="Beauty & Personal Care", 0.3*H3, C3="Sports & Fitness", 0.2*H3, TRUE, 0.15*H3), 2) -> #NAME? | J3: Credit Card | K3: Fulfilled by Amazon | L3: Delivered | M3: Karnataka
A4: IN-2024-1003 | B4: 45300 | C4: Home & Kitchen | D4: Prestige Iris 750W Mixer Grinder | E4: 1 | F4: 3299 | G4: 0.15 | H4: =ROUND(E4*F4*(1-G4), 2) -> 2804.15 | I4: =ROUND(_xludf.IFS(L4="Cancelled", 0, L4="Returned", -0.1*H4, C4="Electronics", 0.14*H4, C4="Appliances", 0.16*H4, C4="Fashion", 0.26*H4, C4="Home & Kitchen", 0.22*H4, C4="Beauty & Personal Care", 0.3*H4, C4="Sports & Fitness", 0.2*H4, TRUE, 0.15*H4), 2) -> #NAME? | J4: Net Banking | K4: Merchant | L4: Delivered | M4: Tamil Nadu
A5: IN-2024-1004 | B5: 45302 | C5: Beauty & Personal Care | D5: Mamaearth Onion Hair Fall Control Shampoo | E5: 3 | F5: 399 | G5: 0.05 | H5: =ROUND(E5*F5*(1-G5), 2) -> 1137.15 | I5: =ROUND(_xludf.IFS(L5="Cancelled", 0, L5="Returned", -0.1*H5, C5="Electronics", 0.14*H5, C5="Appliances", 0.16*H5, C5="Fashion", 0.26*H5, C5="Home & Kitchen", 0.22*H5, C5="Beauty & Personal Care", 0.3*H5, C5="Sports & Fitness", 0.2*H5, TRUE, 0.15*H5), 2) -> #NAME? | J5: Cash on Delivery | K5: Fulfilled by Amazon | L5: Delivered | M5: Uttar Pradesh
A6: IN-2024-1005 | B6: 45305 | C6: Appliances | D6: Philips Digital Air Fryer HD9200 | E6: 1 | F6: 7999 | G6: 0.25 | H6: =ROUND(E6*F6*(1-G6), 2) -> 5999.25 | I6: =ROUND(_xludf.IFS(L6="Cancelled", 0, L6="Returned", -0.1*H6, C6="Electronics", 0.14*H6, C6="Appliances", 0.16*H6, C6="Fashion", 0.26*H6, C6="Home & Kitchen", 0.22*H6, C6="Beauty & Personal Care", 0.3*H6, C6="Sports & Fitness", 0.2*H6, TRUE, 0.15*H6), 2) -> #NAME? | J6: Credit Card | K6: Fulfilled by Amazon | L6: Delivered | M6: Delhi
A7: IN-2024-1006 | B7: 45307 | C7: Electronics | D7: OnePlus Nord CE 3 Lite 5G | E7: 1 | F7: 19999 | G7: 0.08 | H7: =ROUND(E7*F7*(1-G7), 2) -> 18399.08 | I7: =ROUND(_xludf.IFS(L7="Cancelled", 0, L7="Returned", -0.1*H7, C7="Electronics", 0.14*H7, C7="Appliances", 0.16*H7, C7="Fashion", 0.26*H7, C7="Home & Kitchen", 0.22*H7, C7="Beauty & Personal Care", 0.3*H7, C7="Sports & Fitness", 0.2*H7, TRUE, 0.15*H7), 2) -> #NAME? | J7: Amazon Pay | K7: Fulfilled by Amazon | L7: Delivered | M7: Telangana
A8: IN-2024-1007 | B8: 45310 | C8: Sports & Fitness | D8: Boldfit Resistance Bands Set | E8: 2 | F8: 499 | G8: 0.1 | H8: =ROUND(E8*F8*(1-G8), 2) -> 898.2 | I8: =ROUND(_xludf.IFS(L8="Cancelled", 0, L8="Returned", -0.1*H8, C8="Electronics", 0.14*H8, C8="Appliances", 0.16*H8, C8="Fashion", 0.26*H8, C8="Home & Kitchen", 0.22*H8, C8="Beauty & Personal Care", 0.3*H8, C8="Sports & Fitness", 0.2*H8, TRUE, 0.15*H8), 2) -> #NAME? | J8: UPI | K8: Merchant | L8: Delivered | M8: Gujarat
A9: IN-2024-1008 | B9: 45312 | C9: Fashion | D9: Biba Women Printed Straight Kurta | E9: 2 | F9: 1299 | G9: 0.3 | H9: =ROUND(E9*F9*(1-G9), 2) -> 1818.6 | I9: =ROUND(_xludf.IFS(L9="Cancelled", 0, L9="Returned", -0.1*H9, C9="Electronics", 0.14*H9, C9="Appliances", 0.16*H9, C9="Fashion", 0.26*H9, C9="Home & Kitchen", 0.22*H9, C9="Beauty & Personal Care", 0.3*H9, C9="Sports & Fitness", 0.2*H9, TRUE, 0.15*H9), 2) -> #NAME? | J9: Credit Card | K9: Fulfilled by Amazon | L9: Returned | M9: West Bengal
A10: IN-2024-1009 | B10: 45315 | C10: Home & Kitchen | D10: Pigeon Stainless Steel Cookware Set 3 Pcs | E10: 1 | F10: 1899 | G10: 0.15 | H10: =ROUND(E10*F10*(1-G10), 2) -> 1614.15 | I10: =ROUND(_xludf.IFS(L10="Cancelled", 0, L10="Returned", -0.1*H10, C10="Electronics", 0.14*H10, C10="Appliances", 0.16*H10, C10="Fashion", 0.26*H10, C10="Home & Kitchen", 0.22*H10, C10="Beauty & Personal Care", 0.3*H10, C10="Sports & Fitness", 0.2*H10, TRUE, 0.15*H10), 2) -> #NAME? | J10: UPI | K10: Fulfilled by Amazon | L10: Delivered | M10: Kerala
A11: IN-2024-1010 | B11: 45317 | C11: Electronics | D11: Noise ColorFit Pulse 2 Max Smartwatch | E11: 1 | F11: 1799 | G11: 0.2 | H11: =ROUND(E11*F11*(1-G11), 2) -> 1439.2 | I11: =ROUND(_xludf.IFS(L11="Cancelled", 0, L11="Returned", -0.1*H11, C11="Electronics", 0.14*H11, C11="Appliances", 0.16*H11, C11="Fashion", 0.26*H11, C11="Home & Kitchen", 0.22*H11, C11="Beauty & Personal Care", 0.3*H11, C11="Sports & Fitness", 0.2*H11, TRUE, 0.15*H11), 2) -> #NAME? | J11: Debit Card | K11: Merchant | L11: Delivered | M11: Rajasthan
A12: IN-2024-1011 | B12: 45320 | C12: Beauty & Personal Care | D12: Lakme Absolute Matte Lipstick | E12: 4 | F12: 650 | G12: 0.1 | H12: =ROUND(E12*F12*(1-G12), 2) -> 2340 | I12: =ROUND(_xludf.IFS(L12="Cancelled", 0, L12="Returned", -0.1*H12, C12="Electronics", 0.14*H12, C12="Appliances", 0.16*H12, C12="Fashion", 0.26*H12, C12="Home & Kitchen", 0.22*H12, C12="Beauty & Personal Care", 0.3*H12, C12="Sports & Fitness", 0.2*H12, TRUE, 0.15*H12), 2) -> #NAME? | J12: Cash on Delivery | K12: Fulfilled by Amazon | L12: Delivered | M12: Maharashtra
A13: IN-2024-1012 | B13: 45322 | C13: Appliances | D13: Bajaj Splendora 3L Instant Water Heater | E13: 1 | F13: 2899 | G13: 0.18 | H13: =ROUND(E13*F13*(1-G13), 2) -> 2377.18 | I13: =ROUND(_xludf.IFS(L13="Cancelled", 0, L13="Returned", -0.1*H13, C13="Electronics", 0.14*H13, C13="Appliances", 0.16*H13, C13="Fashion", 0.26*H13, C13="Home & Kitchen", 0.22*H13, C13="Beauty & Personal Care", 0.3*H13, C13="Sports & Fitness", 0.2*H13, TRUE, 0.15*H13), 2) -> #NAME? | J13: UPI | K13: Fulfilled by Amazon | L13: Delivered | M13: Karnataka
... A501: IN-2026-1500 | B501: 46387 | C501: Electronics | D501: Sony WH-1000XM5 Wireless ANC Headphones | E501: 1 | F501: 29990 | G501: 0.1 | H501: =ROUND(E501*F501*(1-G501), 2) -> 26991 | I501: =ROUND(_xludf.IFS(L501="Cancelled", 0, L501="Returned", -0.1*H501, C501="Electronics", 0.14*H501, C501="Appliances", 0.16*H501, C501="Fashion", 0.26*H501, C501="Home & Kitchen", 0.22*H501, C501="Beauty & Personal Care", 0.3*H501, C501="Sports & Fitness", 0.2*H501, TRUE, 0.15*H501), 2) -> #NAME? | J501: Amazon Pay | K501: Fulfilled by Amazon | L501: In Transit | M501: Maharashtra

Sheet Management_Summary
B2: AMAZON INDIA SALES MANAGEMENT DASHBOARD | EXECUTIVE SUMMARY
B3: Reporting Period: 2024 – 2026 | Currency: INR (₹) | Data Source: Amazon Seller Central | Prepared for Power BI Executive Review
B5: TOTAL REVENUE | E5: TOTAL UNITS SOLD | I5: NET PROFIT MARGIN | L5: ORDER RETURN RATE
B6: =SUM(object1!H2:H501) -> 2165463.4 | E6: =SUM(object1!E2:E501) -> 810 | I6: =SUM(object1!I2:I501)/SUM(object1!H2:H501) -> #NAME? | L6: =COUNTIF(object1!L2:L501,"Returned")/COUNTA(object1!L2:L501) -> 0.05
B8: FULFILLMENT & ORDER STATUS ANALYSIS | I8: SALES & PROFIT TREND BY PERIOD (2024–2026)
B9: Channel / Order Status | C9: Orders | D9: Units | E9: Revenue (INR) | F9: Profit (INR) | G9: Delivery / Share Rate | I9: Sales Period | J9: Orders | K9: Units | L9: Revenue (INR) | M9: Profit (INR) | N9: Profit Margin
B10: Fulfilled by Amazon (FBA) | C10: =COUNTIF(object1!$K$2:$K$501, "Fulfilled by Amazon") -> 381 | D10: =SUMIF(object1!$K$2:$K$501, "Fulfilled by Amazon", object1!$E$2:$E$501) -> 615 | E10: =SUMIF(object1!$K$2:$K$501, "Fulfilled by Amazon", object1!$H$2:$H$501) -> 1843557.6 | F10: =SUMIF(object1!$K$2:$K$501, "Fulfilled by Amazon", object1!$I$2:$I$501) -> #NAME? | G10: =COUNTIFS(object1!$K$2:$K$501, "Fulfilled by Amazon", object1!$L$2:$L$501, "Delivered")/COUNTIF(object1!$K$2:$K$501, "Fulfilled by Amazon") -> 0.93700787 | I10: 2024 H1 (Jan–Jun 2024) | J10: =COUNTIFS(object1!$B$2:$B$501, ">=2024-01-01", object1!$B$2:$B$501, "<=2024-06-30") -> 71 | K10: =SUMIFS(object1!$E$2:$E$501, object1!$B$2:$B$501, ">=2024-01-01", object1!$B$2:$B$501, "<=2024-06-30") -> 117 | L10: =SUMIFS(object1!$H$2:$H$501, object1!$B$2:$B$501, ">=2024-01-01", object1!$B$2:$B$501, "<=2024-06-30") -> 335312.69 | M10: =SUMIFS(object1!$I$2:$I$501, object1!$B$2:$B$501, ">=2024-01-01", object1!$B$2:$B$501, "<=2024-06-30") -> #NAME? | N10: =IFERROR(M10/L10, 0) -> 0
B11: Merchant Fulfilled (FBM) | C11: =COUNTIF(object1!$K$2:$K$501, "Merchant") -> 119 | D11: =SUMIF(object1!$K$2:$K$501, "Merchant", object1!$E$2:$E$501) -> 195 | E11: =SUMIF(object1!$K$2:$K$501, "Merchant", object1!$H$2:$H$501) -> 321905.84 | F11: =SUMIF(object1!$K$2:$K$501, "Merchant", object1!$I$2:$I$501) -> #NAME? | G11: =COUNTIFS(object1!$K$2:$K$501, "Merchant", object1!$L$2:$L$501, "Delivered")/COUNTIF(object1!$K$2:$K$501, "Merchant") -> 0.68067227 | I11: 2024 H2 (Jul–Dec 2024) | J11: =COUNTIFS(object1!$B$2:$B$501, ">=2024-07-01", object1!$B$2:$B$501, "<=2024-12-31") -> 73 | K11: =SUMIFS(object1!$E$2:$E$501, object1!$B$2:$B$501, ">=2024-07-01", object1!$B$2:$B$501, "<=2024-12-31") -> 116 | L11: =SUMIFS(object1!$H$2:$H$501, object1!$B$2:$B$501, ">=2024-07-01", object1!$B$2:$B$501, "<=2024-12-31") -> 258814.67 | M11: =SUMIFS(object1!$I$2:$I$501, object1!$B$2:$B$501, ">=2024-07-01", object1!$B$2:$B$501, "<=2024-12-31") -> #NAME? | N11: =IFERROR(M11/L11, 0) -> 0
B12: Status: Delivered Orders | C12: =COUNTIF(object1!$L$2:$L$501, "Delivered") -> 438 | D12: =SUMIF(object1!$L$2:$L$501, "Delivered", object1!$E$2:$E$501) -> 712 | E12: =SUMIF(object1!$L$2:$L$501, "Delivered", object1!$H$2:$H$501) -> 1978538.4 | F12: =SUMIF(object1!$L$2:$L$501, "Delivered", object1!$I$2:$I$501) -> #NAME? | G12: =COUNTIF(object1!$L$2:$L$501, "Delivered")/COUNTA(object1!$L$2:$L$501) -> 0.876 | I12: 2025 H1 (Jan–Jun 2025) | J12: =COUNTIFS(object1!$B$2:$B$501, ">=2025-01-01", object1!$B$2:$B$501, "<=2025-06-30") -> 73 | K12: =SUMIFS(object1!$E$2:$E$501, object1!$B$2:$B$501, ">=2025-01-01", object1!$B$2:$B$501, "<=2025-06-30") -> 119 | L12: =SUMIFS(object1!$H$2:$H$501, object1!$B$2:$B$501, ">=2025-01-01", object1!$B$2:$B$501, "<=2025-06-30") -> 346537.91 | M12: =SUMIFS(object1!$I$2:$I$501, object1!$B$2:$B$501, ">=2025-01-01", object1!$B$2:$B$501, "<=2025-06-30") -> #NAME? | N12: =IFERROR(M12/L12, 0) -> 0
B13: Status: Returned Orders | C13: =COUNTIF(object1!$L$2:$L$501, "Returned") -> 25 | D13: =SUMIF(object1!$L$2:$L$501, "Returned", object1!$E$2:$E$501) -> 41 | E13: =SUMIF(object1!$L$2:$L$501, "Returned", object1!$H$2:$H$501) -> 34780.3 | F13: =SUMIF(object1!$L$2:$L$501, "Returned", object1!$I$2:$I$501) -> #NAME? | G13: =COUNTIF(object1!$L$2:$L$501, "Returned")/COUNTA(object1!$L$2:$L$501) -> 0.05 | I13: 2025 H2 (Jul–Dec 2025) | J13: =COUNTIFS(object1!$B$2:$B$501, ">=2025-07-01", object1!$B$2:$B$501, "<=2025-12-31") -> 73 | K13: =SUMIFS(object1!$E$2:$E$501, object1!$B$2:$B$501, ">=2025-07-01", object1!$B$2:$B$501, "<=2025-12-31") -> 118 | L13: =SUMIFS(object1!$H$2:$H$501, object1!$B$2:$B$501, ">=2025-07-01", object1!$B$2:$B$501, "<=2025-12-31") -> 326879.14 | M13: =SUMIFS(object1!$I$2:$I$501, object1!$B$2:$B$501, ">=2025-07-01", object1!$B$2:$B$501, "<=2025-12-31") -> #NAME? | N13: =IFERROR(M13/L13, 0) -> 0
B14: Status: Cancelled & Pending | C14: =COUNTIFS(object1!$L$2:$L$501, "<>Delivered", object1!$L$2:$L$501, "<>Returned", object1!$L$2:$L$501, "<>") -> 37 | D14: =SUMIFS(object1!$E$2:$E$501, object1!$L$2:$L$501, "<>Delivered", object1!$L$2:$L$501, "<>Returned") -> 57 | E14: =SUMIFS(object1!$H$2:$H$501, object1!$L$2:$L$501, "<>Delivered", object1!$L$2:$L$501, "<>Returned") -> 152144.73 | F14: =SUMIFS(object1!$I$2:$I$501, object1!$L$2:$L$501, "<>Delivered", object1!$L$2:$L$501, "<>Returned") -> #NAME? | G14: =C14/COUNTA(object1!$L$2:$L$501) -> 0.074 | I14: 2026 YTD (Jan–Mar 2026) | J14: =COUNTIFS(object1!$B$2:$B$501, ">=2026-01-01", object1!$B$2:$B$501, "<=2026-12-31") -> 210 | K14: =SUMIFS(object1!$E$2:$E$501, object1!$B$2:$B$501, ">=2026-01-01", object1!$B$2:$B$501, "<=2026-12-31") -> 340 | L14: =SUMIFS(object1!$H$2:$H$501, object1!$B$2:$B$501, ">=2026-01-01", object1!$B$2:$B$501, "<=2026-12-31") -> 897919 | M14: =SUMIFS(object1!$I$2:$I$501, object1!$B$2:$B$501, ">=2026-01-01", object1!$B$2:$B$501, "<=2026-12-31") -> #NAME? | N14: =IFERROR(M14/L14, 0) -> 0
B15: Total / Portfolio Overview | C15: =COUNTA(object1!$L$2:$L$501) -> 500 | D15: =SUM(object1!$E$2:$E$501) -> 810 | E15: =SUM(object1!$H$2:$H$501) -> 2165463.4 | F15: =SUM(object1!$I$2:$I$501) -> #NAME? | G15: =COUNTIF(object1!$L$2:$L$501, "Delivered")/COUNTA(object1!$L$2:$L$501) -> 0.876 | I15: Total Period Performance | J15: =SUM(J10:J14) -> 500 | K15: =SUM(K10:K14) -> 810 | L15: =SUM(L10:L14) -> 2165463.4 | M15: =SUM(M10:M14) -> #NAME? | N15: =IFERROR(M15/L15, 0) -> 0
B17: CATEGORY PERFORMANCE BREAKDOWN | I17: REGIONAL SALES BY STATE (TOP STATES & OTHER)
B18: Category | C18: Orders | D18: Units | E18: Total Revenue (INR) | F18: Net Profit (INR) | G18: Profit Margin | I18: State / Territory | J18: Orders | K18: Units | L18: Total Revenue (INR) | M18: Net Profit (INR) | N18: Profit Margin
B19: Electronics | C19: =COUNTIF(object1!$C$2:$C$501, B19) -> 89 | D19: =SUMIF(object1!$C$2:$C$501, B19, object1!$E$2:$E$501) -> 130 | E19: =SUMIF(object1!$C$2:$C$501, B19, object1!$H$2:$H$501) -> 760481.59 | F19: =SUMIF(object1!$C$2:$C$501, B19, object1!$I$2:$I$501) -> #NAME? | G19: =IFERROR(F19/E19, 0) -> 0 | I19: Maharashtra | J19: =COUNTIF(object1!$M$2:$M$501, I19) -> 90 | K19: =SUMIF(object1!$M$2:$M$501, I19, object1!$E$2:$E$501) -> 126 | L19: =SUMIF(object1!$M$2:$M$501, I19, object1!$H$2:$H$501) -> 751267.58 | M19: =SUMIF(object1!$M$2:$M$501, I19, object1!$I$2:$I$501) -> #NAME? | N19: =IFERROR(M19/L19, 0) -> 0
B20: Appliances | C20: =COUNTIF(object1!$C$2:$C$501, B20) -> 82 | D20: =SUMIF(object1!$C$2:$C$501, B20, object1!$E$2:$E$501) -> 92 | E20: =SUMIF(object1!$C$2:$C$501, B20, object1!$H$2:$H$501) -> 828543.62 | F20: =SUMIF(object1!$C$2:$C$501, B20, object1!$I$2:$I$501) -> #NAME? | G20: =IFERROR(F20/E20, 0) -> 0 | I20: Karnataka | J20: =COUNTIF(object1!$M$2:$M$501, I20) -> 74 | K20: =SUMIF(object1!$M$2:$M$501, I20, object1!$E$2:$E$501) -> 104 | L20: =SUMIF(object1!$M$2:$M$501, I20, object1!$H$2:$H$501) -> 355349.31 | M20: =SUMIF(object1!$M$2:$M$501, I20, object1!$I$2:$I$501) -> #NAME? | N20: =IFERROR(M20/L20, 0) -> 0
B21: Fashion | C21: =COUNTIF(object1!$C$2:$C$501, B21) -> 83 | D21: =SUMIF(object1!$C$2:$C$501, B21, object1!$E$2:$E$501) -> 123 | E21: =SUMIF(object1!$C$2:$C$501, B21, object1!$H$2:$H$501) -> 138785.41 | F21: =SUMIF(object1!$C$2:$C$501, B21, object1!$I$2:$I$501) -> #NAME? | G21: =IFERROR(F21/E21, 0) -> 0 | I21: Delhi | J21: =COUNTIF(object1!$M$2:$M$501, I21) -> 73 | K21: =SUMIF(object1!$M$2:$M$501, I21, object1!$E$2:$E$501) -> 116 | L21: =SUMIF(object1!$M$2:$M$501, I21, object1!$H$2:$H$501) -> 348855.26 | M21: =SUMIF(object1!$M$2:$M$501, I21, object1!$I$2:$I$501) -> #NAME? | N21: =IFERROR(M21/L21, 0) -> 0
B22: Home & Kitchen | C22: =COUNTIF(object1!$C$2:$C$501, B22) -> 83 | D22: =SUMIF(object1!$C$2:$C$501, B22, object1!$E$2:$E$501) -> 125 | E22: =SUMIF(object1!$C$2:$C$501, B22, object1!$H$2:$H$501) -> 135444.96 | F22: =SUMIF(object1!$C$2:$C$501, B22, object1!$I$2:$I$501) -> #NAME? | G22: =IFERROR(F22/E22, 0) -> 0 | I22: Telangana | J22: =COUNTIF(object1!$M$2:$M$501, I22) -> 41 | K22: =SUMIF(object1!$M$2:$M$501, I22, object1!$E$2:$E$501) -> 60 | L22: =SUMIF(object1!$M$2:$M$501, I22, object1!$H$2:$H$501) -> 239493.5 | M22: =SUMIF(object1!$M$2:$M$501, I22, object1!$I$2:$I$501) -> #NAME? | N22: =IFERROR(M22/L22, 0) -> 0
B23: Beauty & Personal Care | C23: =COUNTIF(object1!$C$2:$C$501, B23) -> 83 | D23: =SUMIF(object1!$C$2:$C$501, B23, object1!$E$2:$E$501) -> 190 | E23: =SUMIF(object1!$C$2:$C$501, B23, object1!$H$2:$H$501) -> 81717.17 | F23: =SUMIF(object1!$C$2:$C$501, B23, object1!$I$2:$I$501) -> #NAME? | G23: =IFERROR(F23/E23, 0) -> 0 | I23: Tamil Nadu | J23: =COUNTIF(object1!$M$2:$M$501, I23) -> 48 | K23: =SUMIF(object1!$M$2:$M$501, I23, object1!$E$2:$E$501) -> 80 | L23: =SUMIF(object1!$M$2:$M$501, I23, object1!$H$2:$H$501) -> 143682.17 | M23: =SUMIF(object1!$M$2:$M$501, I23, object1!$I$2:$I$501) -> #NAME? | N23: =IFERROR(M23/L23, 0) -> 0
B24: Sports & Fitness | C24: =COUNTIF(object1!$C$2:$C$501, B24) -> 80 | D24: =SUMIF(object1!$C$2:$C$501, B24, object1!$E$2:$E$501) -> 150 | E24: =SUMIF(object1!$C$2:$C$501, B24, object1!$H$2:$H$501) -> 220490.66 | F24: =SUMIF(object1!$C$2:$C$501, B24, object1!$I$2:$I$501) -> #NAME? | G24: =IFERROR(F24/E24, 0) -> 0 | I24: Other States | J24: =COUNTIFS(object1!$M$2:$M$501, "<>Maharashtra", object1!$M$2:$M$501, "<>Karnataka", object1!$M$2:$M$501, "<>Delhi", object1!$M$2:$M$501, "<>Telangana", object1!$M$2:$M$501, "<>Tamil Nadu", object1!$M$2:$M$501, "<>") -> 174 | K24: =SUM(object1!$E$2:$E$501)-SUM(K19:K23) -> 324 | L24: =SUM(object1!$H$2:$H$501)-SUM(L19:L23) -> 326815.59 | M24: =SUM(object1!$I$2:$I$501)-SUM(M19:M23) -> #NAME? | N24: =IFERROR(M24/L24, 0) -> 0
B25: Total Category Sales | C25: =SUM(C19:C24) -> 500 | D25: =SUM(D19:D24) -> 810 | E25: =SUM(E19:E24) -> 2165463.4 | F25: =SUM(F19:F24) -> #NAME? | G25: =IFERROR(F25/E25, 0) -> 0 | I25: Total Regional Sales | J25: =SUM(J19:J24) -> 500 | K25: =SUM(K19:K24) -> 810 | L25: =SUM(L19:L24) -> 2165463.4 | M25: =SUM(M19:M24) -> #NAME? | N25: =IFERROR(M25/L25, 0) -> 0
B26: * Metrics reflect Amazon India transactions across FY 2024–2026. All financial values in INR (₹). Formatted for seamless ingestion into Power BI data models.
